durabletask/__init__.py
durabletask/client.py
durabletask/task.py
durabletask/worker.py
durabletask/entities/__init__.py
durabletask/entities/durable_entity.py
durabletask/entities/entity_context.py
durabletask/entities/entity_instance_id.py
durabletask/entities/entity_lock.py
durabletask/internal/entity_state_shim.py
durabletask/internal/exceptions.py
durabletask/internal/grpc_interceptor.py
durabletask/internal/helpers.py
durabletask/internal/orchestration_entity_context.py
durabletask/internal/orchestrator_service_pb2.py
durabletask/internal/orchestrator_service_pb2.pyi
durabletask/internal/orchestrator_service_pb2_grpc.py
durabletask/internal/shared.py
durabletask-1.0.0.dist-info/licenses/LICENSE
durabletask-1.0.0.dist-info/METADATA
durabletask-1.0.0.dist-info/WHEEL
durabletask-1.0.0.dist-info/top_level.txt
durabletask-1.0.0.dist-info/RECORD
