Metadata-Version: 2.4
Name: durabletask
Version: 1.0.0
Summary: A Durable Task Client SDK for Python
License:     MIT License
Project-URL: repository, https://github.com/microsoft/durabletask-python
Project-URL: changelog, https://github.com/microsoft/durabletask-python/blob/main/CHANGELOG.md
Keywords: durable,task,workflow
Classifier: Development Status :: 5 - Production/Stable
Classifier: Programming Language :: Python :: 3
Classifier: License :: OSI Approved :: MIT License
Requires-Python: >=3.10
License-File: LICENSE
Requires-Dist: grpcio
Requires-Dist: protobuf
Requires-Dist: asyncio
Requires-Dist: packaging
Dynamic: license-file
